CHANGES.rst
MANIFEST.in
README.rst
bootstrap.py
buildout.cfg
setup.py
docs/LICENSE.GPL
docs/LICENSE.txt
src/collective/__init__.py
src/collective.indexing.egg-info/PKG-INFO
src/collective.indexing.egg-info/SOURCES.txt
src/collective.indexing.egg-info/dependency_links.txt
src/collective.indexing.egg-info/entry_points.txt
src/collective.indexing.egg-info/namespace_packages.txt
src/collective.indexing.egg-info/not-zip-safe
src/collective.indexing.egg-info/requires.txt
src/collective.indexing.egg-info/top_level.txt
src/collective/indexing/__init__.py
src/collective/indexing/config.py
src/collective/indexing/configure.zcml
src/collective/indexing/indexer.py
src/collective/indexing/interfaces.py
src/collective/indexing/monkey.py
src/collective/indexing/queue.py
src/collective/indexing/subscribers.py
src/collective/indexing/subscribers.zcml
src/collective/indexing/transactions.py
src/collective/indexing/Extensions/Install.py
src/collective/indexing/Extensions/__init__.py
src/collective/indexing/tests/__init__.py
src/collective/indexing/tests/base.py
src/collective/indexing/tests/browser.txt
src/collective/indexing/tests/change-notes.txt
src/collective/indexing/tests/content.py
src/collective/indexing/tests/layer.py
src/collective/indexing/tests/moveonwftransition.txt
src/collective/indexing/tests/test_doctest.py
src/collective/indexing/tests/test_integration.py
src/collective/indexing/tests/test_lifecycle.py
src/collective/indexing/tests/test_queue.py
src/collective/indexing/tests/test_subscribers.py
src/collective/indexing/tests/test_transactions.py
src/collective/indexing/tests/utils.py
var/README.txt