Metadata-Version: 1.1
Name: collective.indexing
Version: 2.0
Summary: Abstract framework for queueing, optimizing and dispatching index operations for Plone content.
Home-page: https://github.com/collective/collective.indexing
Author: Plone Foundation
Author-email: plone-developers@lists.sourceforge.net
License: GPL
Keywords: plone cmf zope indexing queueing catalog asynchronous
Platform: Any
Classifier: Development Status :: 5 - Production/Stable
Classifier: Environment :: Web Environment
Classifier: Framework :: Plone
Classifier: Intended Audience :: Developers
Classifier: License :: OSI Approved :: GNU General Public License (GPL)
Classifier: Operating System :: OS Independent
Classifier: Programming Language :: Python
